GPTAgent/GPTAgent.py
GPTAgent/__init__.py
gptagent-0.0.17.dist-info/METADATA
gptagent-0.0.17.dist-info/WHEEL
gptagent-0.0.17.dist-info/licenses/LICENSE
gptagent-0.0.17.dist-info/RECORD
