Metadata-Version: 2.1
Name: GPTAgent
Version: 0.0.17
Summary: A small and simple way to generate a ChatGPT agent
Project-URL: Homepage, https://github.com/inteligenciamilgrau/GPTAgent
Author-email: Inteligência Mil Grau <inteligenciamilgrau@gmail.com>
License-File: LICENSE
Classifier: License :: OSI Approved :: MIT License
Classifier: Operating System :: OS Independent
Classifier: Programming Language :: Python :: 3
Requires-Python: >=3.7
